keyserver_client/__init__.py
keyserver_client/command_line.py
keyserver_client-0.3.3.dist-info/METADATA
keyserver_client-0.3.3.dist-info/WHEEL
keyserver_client-0.3.3.dist-info/entry_points.txt
keyserver_client-0.3.3.dist-info/top_level.txt
keyserver_client-0.3.3.dist-info/RECORD
