Metadata-Version: 2.1
Name: keyserver-client
Version: 0.3.3
Summary: Client for the RG Keyserver
Home-page: https://github.com/realgeeks/keyserver_client
Author: Kevin McCarthy
Author-email: kevin@realgeeks.com
License: UNKNOWN
Platform: UNKNOWN
